vcforge/__init__.py
vcforge/_version.py
vcforge/old_parsing.py
vcforge/parsing.py
vcforge/test.py
vcforge/utils.py
vcforge/vcforge.py
vcforge-0.1.8.dist-info/LICENSE
vcforge-0.1.8.dist-info/METADATA
vcforge-0.1.8.dist-info/WHEEL
vcforge-0.1.8.dist-info/RECORD
